canaries/__init__.py
canaries/canaries.py
canaries-0.2.0.dist-info/LICENSE
canaries-0.2.0.dist-info/METADATA
canaries-0.2.0.dist-info/WHEEL
canaries-0.2.0.dist-info/top_level.txt
canaries-0.2.0.dist-info/RECORD
