Metadata-Version: 2.1
Name: canaries
Version: 0.2.0
Summary: Python library for choosing and loading dynamic library files compatible with the operating environment.
Home-page: https://github.com/reity/canaries
Author: Andrei Lapets
Author-email: a@lapets.io
License: MIT
Platform: UNKNOWN
